{"wrapper":"div.collection-wrapper.wrapper","sections":{"collection-header":{"type":"template--collection--header","blocks":{"collection-image":{"type":"collection_image","settings":{"collection-image-size":"20vh"}},"title":{"type":"title","disabled":true,"settings":{}},"description":{"type":"description","disabled":true,"settings":{}}},"block_order":["collection-image","title","description"],"settings":{}},"product-grid":{"type":"template--collection","blocks":{"product_card_image":{"type":"product_card_image","settings":{"enable_badges":true}},"product_card_title":{"type":"product_card_title","settings":{}},"product_card_price":{"type":"product_card_price","settings":{}},"product_card_button":{"type":"product_card_button","settings":{}}},"block_order":["product_card_image","product_card_title","product_card_price","product_card_button"],"settings":{"desktop-products-per-row":3,"tablet-products-per-row":2,"mobile-products-per-row":1,"products-per-page":4,"pagination_options":"pagination_default","desktop_position":"sidebar","enable_collection_title":true,"enable_collection_description":true,"enable_filtering":false,"hide_mobile_filters":true,"enable_sorting":false}},"countdown-timer":{"type":"countdown-timer","blocks":{"countdown-timer-0":{"type":"subheading","settings":{"subheading":"Subheading"}},"countdown-timer-1":{"type":"heading","settings":{"heading":"Countdown timer"}},"countdown-timer-2":{"type":"countdown_timer","settings":{"end_date":"","end_time":"","hide_when_complete":false,"time_labels":"show"}},"countdown-timer-3":{"type":"text","settings":{"text":"Grab the offer before it's gone"}},"timer_complete_message":{"type":"timer_complete_message","settings":{"text":"Our newest launch has just gone live.. Don't miss out on the next!"}},"countdown-timer-4":{"type":"button","settings":{"label":"Shop now","link":"shopify:\/\/collections\/all"}}},"block_order":["countdown-timer-0","countdown-timer-1","countdown-timer-2","countdown-timer-3","timer_complete_message","countdown-timer-4"],"disabled":true,"settings":{"color_scheme":"light","text_overlapping_image":false,"section_width":"full","layout":"image_on_right","text_alignment":"center"}},"blog-posts":{"type":"blog--blog-posts","blocks":{"blog-posts-0":{"type":"blog","settings":{"blog":""}}},"block_order":["blog-posts-0"],"disabled":true,"settings":{"colors":"white","title":"From the blog","richtext":"","blog_show_date":false,"post_limit":3}},"b2ff9743-0cf8-4748-94b0-02e35cda06f2":{"type":"text--rich-text","settings":{"colors":"white","title":"","text":"","button_label":"Proceed to Checkout","button_link":"https:\/\/sea2table.com\/cart"}},"onlytext_GnH8gk":{"type":"Onlytext","settings":{"metafieldtext":""}}},"order":["collection-header","product-grid","countdown-timer","blog-posts","b2ff9743-0cf8-4748-94b0-02e35cda06f2","onlytext_GnH8gk"]}